geepers/__init__.py
geepers/classifier.py
geepers/data_manager.py
geepers/gp.py
geepers/gp2.py
geepers/hyper_heuristics.py
geepers_pkg-0.0.2.dist-info/LICENSE
geepers_pkg-0.0.2.dist-info/METADATA
geepers_pkg-0.0.2.dist-info/WHEEL
geepers_pkg-0.0.2.dist-info/top_level.txt
geepers_pkg-0.0.2.dist-info/RECORD
