Metadata-Version: 2.1
Name: geepers-pkg
Version: 0.0.2
Summary: Package to create generation constructive hyper-heuristics.
Home-page: https://github.com/AndreasNel/geepers
Author: Andreas Nel
Author-email: nel.andreas1@gmail.com
License: UNKNOWN
Platform: UNKNOWN
Classifier: Programming Language :: Python :: 3
Classifier: License :: OSI Approved :: MIT License
Classifier: Operating System :: OS Independent
